{
  "drinks": [
    {
      "id": "7",
      "name": "Gibson Exception\nDirty Martini",
      "recipe": "75 ml Åre Bränneri Number 6 Dry Gin\n15 ml Noilly Prat Dry Vermouth\n5 ml olive brine\nOlives",
      "tech": {
        "camera": "Sony a7II",
        "lens": "Canon EF50 f/1.4",
        "focal": "50mm",
        "aperture": "f/1.7",
        "iso": "320"
      },
      "img": "007.jpg"
    },
    {
      "id": "6",
      "name": "Fräkne Tång\nGin Fizz",
      "recipe": "60 ml Klocktornet Gin Fräkne Tång\n40 ml freshly pressed lemon juice\n30 ml simple syrup\nEgg white",
      "tech": {
        "camera": "Sony a7II",
        "lens": "Canon EF50 f/1.4",
        "focal": "50mm",
        "aperture": "f/1.7",
        "iso": "320"
      },
      "img": "006.jpg"
    },
    {
      "id": "5",
      "name": "ND Forest\nGin & Tonic",
      "recipe": "50 ml Norrbottens Destilleri Forest Dry Gin\n100 ml Ekobryggeriet Spruce Shoots Tonic\nDried orange slice\nJuniper berries\nIce",
      "tech": {
        "camera": "Sony a7II",
        "lens": "Canon EF50 f/1.4",
        "focal": "50mm",
        "aperture": "f/1.7",
        "iso": "320"
      },
      "img": "005.jpg"
    },
    {
      "id": "4",
      "name": "Purity Organic\nDry Martini",
      "recipe": "50 ml Purity Dry Organic Gin\n20 ml Noilly Prat Dry Vermouth\nOlives",
      "tech": {
        "camera": "Sony a7II",
        "lens": "Canon EF50 f/1.4",
        "focal": "50mm",
        "aperture": "f/1.7",
        "iso": "320"
      },
      "img": "004.jpg"
    },
    {
      "id": "3",
      "name": "Hellström\nGibson Martini",
      "recipe": "75 ml Hellström Dry Gin\n15 ml Noilly Prat Dry Vermouth\nPearl onions",
      "tech": {
        "camera": "Sony a7II",
        "lens": "Canon EF50 f/1.4",
        "focal": "50mm",
        "aperture": "f/1.7",
        "iso": "320"
      },
      "img": "003.jpg"
    },
    {
      "id": "2",
      "name": "Lydén Navy\nNegroni",
      "recipe": "25 ml Lydén Distillery Navy Gin\n25 ml Martini Rosso Vermouth\n25 ml Campari\n2 big ice cubes",
      "tech": {
        "camera": "Sony a7II",
        "lens": "Canon EF50 f/1.4",
        "focal": "50mm",
        "aperture": "f/1.7",
        "iso": "320"
      },
      "img": "002.jpg"
    },
    {
      "id": "7",
      "name": "Gibson Exception\nDirty Martini",
      "recipe": "75 ml Åre Bränneri Number 6 Dry Gin\n15 ml Noilly Prat Dry Vermouth\n5 ml olive brine\nOlives",
      "tech": {
        "camera": "Sony a7II",
        "lens": "Canon EF50 f/1.4",
        "focal": "50mm",
        "aperture": "f/1.7",
        "iso": "320"
      },
      "img": "007.jpg"
    },
    {
      "id": "6",
      "name": "Fräkne Tång\nGin Fizz",
      "recipe": "60 ml Klocktornet Gin Fräkne Tång\n40 ml freshly pressed lemon juice\n30 ml simple syrup\nEgg white",
      "tech": {
        "camera": "Sony a7II",
        "lens": "Canon EF50 f/1.4",
        "focal": "50mm",
        "aperture": "f/1.7",
        "iso": "320"
      },
      "img": "006.jpg"
    },
    {
      "id": "5",
      "name": "ND Forest\nGin & Tonic",
      "recipe": "50 ml Norrbottens Destilleri Forest Dry Gin\n100 ml Ekobryggeriet Spruce Shoots Tonic\nDried orange slice\nJuniper berries\nIce",
      "tech": {
        "camera": "Sony a7II",
        "lens": "Canon EF50 f/1.4",
        "focal": "50mm",
        "aperture": "f/1.7",
        "iso": "320"
      },
      "img": "005.jpg"
    },
    {
      "id": "4",
      "name": "Purity Organic\nDry Martini",
      "recipe": "50 ml Purity Dry Organic Gin\n20 ml Noilly Prat Dry Vermouth\nOlives",
      "tech": {
        "camera": "Sony a7II",
        "lens": "Canon EF50 f/1.4",
        "focal": "50mm",
        "aperture": "f/1.7",
        "iso": "320"
      },
      "img": "004.jpg"
    },
    {
      "id": "3",
      "name": "Hellström\nGibson Martini",
      "recipe": "75 ml Hellström Dry Gin\n15 ml Noilly Prat Dry Vermouth\nPearl onions",
      "tech": {
        "camera": "Sony a7II",
        "lens": "Canon EF50 f/1.4",
        "focal": "50mm",
        "aperture": "f/1.7",
        "iso": "320"
      },
      "img": "003.jpg"
    },
    {
      "id": "2",
      "name": "Lydén Navy\nNegroni",
      "recipe": "25 ml Lydén Distillery Navy Gin\n25 ml Martini Rosso Vermouth\n25 ml Campari\n2 big ice cubes",
      "tech": {
        "camera": "Sony a7II",
        "lens": "Canon EF50 f/1.4",
        "focal": "50mm",
        "aperture": "f/1.7",
        "iso": "320"
      },
      "img": "002.jpg"
    }
  ]
}
